src/python-progressbar-simenf05/__init__.py
src/python-progressbar-simenf05/progressbar.py
python_progressbar_simenf05-0.0.1.dist-info/METADATA
python_progressbar_simenf05-0.0.1.dist-info/WHEEL
python_progressbar_simenf05-0.0.1.dist-info/licenses/LICENSE
python_progressbar_simenf05-0.0.1.dist-info/RECORD
